preprocessingtweet/__init__.py
preprocessingtweet/preprocessingFullTweets.py
preprocessingtweet/preprocessingTweetText.py
preprocessingtweet/preprocessingTweets.py
preprocessingtweet-0.1.5.1.dist-info/LICENSE
preprocessingtweet-0.1.5.1.dist-info/METADATA
preprocessingtweet-0.1.5.1.dist-info/WHEEL
preprocessingtweet-0.1.5.1.dist-info/RECORD
